{
    "shape of you": "7qiZfU4dY1lWllzX7mPBI3",
    "california girls": null,
    "yellow by coldplay": "3AJwUDP919kvQ9QcozQPxg",
    "california girls by katy perry": null,
    "hymm for the weekend": null,
    "california gurls": "7DjQUa8BrQevCPtQc0YwmL",
    "a sky full of stars": "0FDzzruyVECATHXKHFs9eJ",
    "ayyy ladies": null,
    "ayyyyy ladies": "4P6BuLsqtg5uISdE77ypI9",
    "ayyyyyy ladies": "4P6BuLsqtg5uISdE77ypI9",
    "sky full of stars": "0FDzzruyVECATHXKHFs9eJ",
    "viva la vida": "1mea3bSkSGXuIRvnydlB5b",
    "yellow": "3AJwUDP919kvQ9QcozQPxg",
    "all i wanted by paramore": "4BbXg5wQqVNPbVEGpjsVnv"
}